{
    "name": "ValleyCraft",
    "icon": "valley:scarecrow",
    "category": "patchouli:other",
    "pages": [
        {
            "type": "patchouli:text",
            "text": "$(o)ValleyCraft is a mod heavily inspired by Stardew Valley. It adds a whole lot of things, from food and equipment for farming to weapons and armor for exploring and dungeon crawling."
        },
        {
            "type": "patchouli:link",
            "url": "https://github.com/l1nkl3/ValleyCraft-Wiki/blob/gh-pages/docs/README.md",
            "text": "$(o)The best way to see how to see all the mod has to offer and how to do certain things, is to check out the wiki.",
            "link_text": "ValleyCraft Wiki"
        }
    ],
    "sortnum": "1"
}